Workbook

Sheet README
A1: Anchored Returns — Pilot Coding Sheet
A2: Version 0.1.2. Companion to Anchored_Returns_Codebook_v0.1.2.docx. Read the codebook before coding.
A4: SHEETS
A5: Cases | B5: One row per order: metadata and every party's ROE number. Derived measures compute automatically.
A6: Passages | B6: One row per paragraph of the ROE section. Tag section, apply every code that fits (0/1), pick one primary code and a stance.
A7: Case_Codes | B7: Automatic. Counts codes per order, using Commission analysis passages only.
A8: Reliability | B8: Enter re-codes (or a second coder) in long format; kappa per code computes automatically.
A9: Summary | B9: Automatic. Pilot-level feasibility and descriptive statistics.
A10: Lists | B10: Dropdown values. Edit here if the codebook changes.
A12: COLOR KEY
A13: Navy header | B13: Input column — you fill these.
A14: Grey header / grey cells | B14: Formula — do not type over.
A15: Yellow row | B15: Example row (EX-01). Shows format. Excluded from Summary. Its numbers come from news sources and must be verified against the order.
A17: CONVENTIONS
A18: Percentages | B18: Type as percentages (9.5%) or fractions (0.095). Never as 9.5 — that becomes 950%.
A19: Blanks | B19: Leave a field blank if the order does not state it. Never fill from a secondary source (Codebook Rule 8).
A20: Case IDs | B20: P01–P15 are pre-filled. Passage IDs: case_id + 3-digit number, e.g. P01-001.
A21: Header comments | B21: Hover over a header with a red corner for its definition.
A23: WORKFLOW PER ORDER
A24: 1 | B24: Locate the ROE section; fill Cases metadata and all numeric fields from the order.
A25: 2 | B25: Read the full ROE section once without coding.
A26: 3 | B26: Enter each paragraph in Passages with its section. Split paragraphs where the commission's own voice begins.
A27: 4 | B27: Code each passage; choose primary code and stance.
A28: 5 | B28: Set decisive_rationale and conclusory_flag in Cases.
A29: 6 | B29: Record minutes spent and anything confusing in notes.
A30: 7 | B30: After five orders: wait 10–14 days, re-code them blind, enter both in Reliability.
A32: INTEGRITY RULES
A33: Hide derived columns | B33: Select the grey formula columns in Cases and hide them (right-click > Hide) until all 15 orders are coded. Code reasoning without seeing where the award lands.
A34: Practice orders | B34: Practise on orders OUTSIDE the sample (e.g., before 2019) in a separate copy of this file. Never practise on sample orders.
A35: Base vs. final ROE | B35: awarded_roe is the base determination. Penalties/rewards go in perf_adjustment_bp. Position measures use the base.

Sheet Cases
A1: case_id | B1: sample_status | C1: state | D1: commission | E1: docket | F1: utility | G1: service | H1: segment | I1: decision_type | J1: open_meeting_date | K1: order_date | L1: order_url | M1: roe_section_pages | N1: requested_roe_initial | O1: requested_roe | P1: utility_witness_low | Q1: utility_witness_high | R1: staff_rec | S1: advocate_rec | T1: other_intervenor_rec | U1: alj_rec | V1: commission_range_low | W1: commission_range_high | X1: awarded_roe | Y1: perf_adjustment_bp | Z1: prior_authorized_roe | AA1: prior_order_date | AB1: ust10_at_prior_order | AC1: nat_avg_cited_in_order | AD1: nat_avg_value_cited | AE1: nat_avg_benchmark | AF1: ust10_at_order | AG1: equity_ratio_awarded | AH1: statutory_peer_mandate | AI1: decisive_rationale | AJ1: conclusory_flag | AK1: commissioner_selection | AL1: coder | AM1: date_coded | AN1: minutes_spent | AO1: sources_notes | AP1: record_midpoint | AQ1: split_position | AR1: dist_to_midpoint | AS1: dist_to_nat_avg | AT1: closer_to | AU1: change_vs_prior | AV1: premium_over_ust10 | AW1: awarded_roe_final | AX1: position_in_range | AY1: dist_to_prior | AZ1: dist_to_alj | BA1: nearest_reference | BB1: months_since_prior | BC1: delta_ust10_since_prior | BD1: request_revision | BE1: rate_regime
A2: EX-01 | B2: Included by design | C2: NH | D2: NH Public Utilities Commission | E2: DE 24-070 | F2: Public Service Co. of NH d/b/a Eversource Energy | G2: Electric | H2: Distribution | I2: Fully litigated | K2: 45863 | N2: 0.108 | O2: 0.103 | P2: 0.103 | Q2: 0.113 | S2: 0.0813 | X2: 0.095 | AE2: 0.0968 | AL2: EXAMPLE | AO2: EXAMPLE ROW — values from secondary sources, NOT from the order. Verify every number against the order before use (Rule 8). Requested 10.3% (lowered from 10.8%) and awarded 9.5%: NH OCA and NH Bulletin, Jul 2025. Advocate 8.13%: NH Bulletin (OCA cites 8.1%). Utility witness range 10.30–11.30%: InDepthNH, Jul 2025. Decision type: OCA described Order No. 28,170 (Jul 25, 2025) as the first fully contested resolution in many years. Prior rate case: DE 19-057 — get prior ROE and date from that order. National benchmark 9.68% = RRA average authorized electric ROE, H1 2025, excluding riders. Staff rec, ALJ rec, range, prior ROE, UST10: to collect. | AP2: =IF(COUNT(O2,R2:T2)=0,"",AVERAGE(O2,R2:T2)) -> 0.09215 | AQ2: =IF(OR(X2="",O2="",S2="",O2=S2),"",(X2-S2)/(O2-S2)) -> 0.63133641 | AR2: =IF(OR(X2="",AP2=""),"",ABS(X2-AP2)) -> 0.00285 | AS2: =IF(OR(X2="",AE2=""),"",ABS(X2-AE2)) -> 0.0018 | AT2: =IF(OR(AR2="",AS2=""),"",IF(AS2<AR2,"National avg",IF(AR2<AS2,"Record midpoint","Tie"))) -> National avg | AU2: =IF(OR(X2="",Z2=""),"",X2-Z2) | AV2: =IF(OR(X2="",AF2=""),"",X2-AF2) | AW2: =IF(X2="","",X2+IF(Y2="",0,Y2)/10000) -> 0.095 | AX2: =IF(OR(X2="",V2="",W2="",W2=V2),"",(X2-V2)/(W2-V2)) | AY2: =IF(OR(X2="",Z2=""),"",ABS(X2-Z2)) | AZ2: =IF(OR(X2="",U2=""),"",ABS(X2-U2)) | BA2: =IF(COUNT(AR2,AS2,AY2,AZ2)<2,"",IF(AR2=MIN(AR2,AS2,AY2,AZ2),"Record midpoint",IF(AS2=MIN(AR2,AS2,AY2,AZ2),"National avg",IF(AY2=MIN(AR2,AS2,AY2,AZ2),"Prior award","ALJ")))) -> National avg | BB2: =IF(OR(K2="",AA2=""),"",(K2-AA2)/30.4375) | BC2: =IF(OR(AF2="",AB2=""),"",AF2-AB2) | BD2: =IF(OR(O2="",N2=""),"",O2-N2) -> -0.005 | BE2: =IF(K2="","",IF(K2<DATE(2022,1,1),"Pre (2019-21)",IF(K2<DATE(2023,1,1),"Transition (2022)","Post (2023-)"))) -> Post (2023-)
A3: P01 | AP3: =IF(COUNT(O3,R3:T3)=0,"",AVERAGE(O3,R3:T3)) | AQ3: =IF(OR(X3="",O3="",S3="",O3=S3),"",(X3-S3)/(O3-S3)) | AR3: =IF(OR(X3="",AP3=""),"",ABS(X3-AP3)) | AS3: =IF(OR(X3="",AE3=""),"",ABS(X3-AE3)) | AT3: =IF(OR(AR3="",AS3=""),"",IF(AS3<AR3,"National avg",IF(AR3<AS3,"Record midpoint","Tie"))) | AU3: =IF(OR(X3="",Z3=""),"",X3-Z3) | AV3: =IF(OR(X3="",AF3=""),"",X3-AF3) | AW3: =IF(X3="","",X3+IF(Y3="",0,Y3)/10000) | AX3: =IF(OR(X3="",V3="",W3="",W3=V3),"",(X3-V3)/(W3-V3)) | AY3: =IF(OR(X3="",Z3=""),"",ABS(X3-Z3)) | AZ3: =IF(OR(X3="",U3=""),"",ABS(X3-U3)) | BA3: =IF(COUNT(AR3,AS3,AY3,AZ3)<2,"",IF(AR3=MIN(AR3,AS3,AY3,AZ3),"Record midpoint",IF(AS3=MIN(AR3,AS3,AY3,AZ3),"National avg",IF(AY3=MIN(AR3,AS3,AY3,AZ3),"Prior award","ALJ")))) | BB3: =IF(OR(K3="",AA3=""),"",(K3-AA3)/30.4375) | BC3: =IF(OR(AF3="",AB3=""),"",AF3-AB3) | BD3: =IF(OR(O3="",N3=""),"",O3-N3) | BE3: =IF(K3="","",IF(K3<DATE(2022,1,1),"Pre (2019-21)",IF(K3<DATE(2023,1,1),"Transition (2022)","Post (2023-)")))
A4: P02 | AP4: =IF(COUNT(O4,R4:T4)=0,"",AVERAGE(O4,R4:T4)) | AQ4: =IF(OR(X4="",O4="",S4="",O4=S4),"",(X4-S4)/(O4-S4)) | AR4: =IF(OR(X4="",AP4=""),"",ABS(X4-AP4)) | AS4: =IF(OR(X4="",AE4=""),"",ABS(X4-AE4)) | AT4: =IF(OR(AR4="",AS4=""),"",IF(AS4<AR4,"National avg",IF(AR4<AS4,"Record midpoint","Tie"))) | AU4: =IF(OR(X4="",Z4=""),"",X4-Z4) | AV4: =IF(OR(X4="",AF4=""),"",X4-AF4) | AW4: =IF(X4="","",X4+IF(Y4="",0,Y4)/10000) | AX4: =IF(OR(X4="",V4="",W4="",W4=V4),"",(X4-V4)/(W4-V4)) | AY4: =IF(OR(X4="",Z4=""),"",ABS(X4-Z4)) | AZ4: =IF(OR(X4="",U4=""),"",ABS(X4-U4)) | BA4: =IF(COUNT(AR4,AS4,AY4,AZ4)<2,"",IF(AR4=MIN(AR4,AS4,AY4,AZ4),"Record midpoint",IF(AS4=MIN(AR4,AS4,AY4,AZ4),"National avg",IF(AY4=MIN(AR4,AS4,AY4,AZ4),"Prior award","ALJ")))) | BB4: =IF(OR(K4="",AA4=""),"",(K4-AA4)/30.4375) | BC4: =IF(OR(AF4="",AB4=""),"",AF4-AB4) | BD4: =IF(OR(O4="",N4=""),"",O4-N4) | BE4: =IF(K4="","",IF(K4<DATE(2022,1,1),"Pre (2019-21)",IF(K4<DATE(2023,1,1),"Transition (2022)","Post (2023-)")))
A5: P03 | AP5: =IF(COUNT(O5,R5:T5)=0,"",AVERAGE(O5,R5:T5)) | AQ5: =IF(OR(X5="",O5="",S5="",O5=S5),"",(X5-S5)/(O5-S5)) | AR5: =IF(OR(X5="",AP5=""),"",ABS(X5-AP5)) | AS5: =IF(OR(X5="",AE5=""),"",ABS(X5-AE5)) | AT5: =IF(OR(AR5="",AS5=""),"",IF(AS5<AR5,"National avg",IF(AR5<AS5,"Record midpoint","Tie"))) | AU5: =IF(OR(X5="",Z5=""),"",X5-Z5) | AV5: =IF(OR(X5="",AF5=""),"",X5-AF5) | AW5: =IF(X5="","",X5+IF(Y5="",0,Y5)/10000) | AX5: =IF(OR(X5="",V5="",W5="",W5=V5),"",(X5-V5)/(W5-V5)) | AY5: =IF(OR(X5="",Z5=""),"",ABS(X5-Z5)) | AZ5: =IF(OR(X5="",U5=""),"",ABS(X5-U5)) | BA5: =IF(COUNT(AR5,AS5,AY5,AZ5)<2,"",IF(AR5=MIN(AR5,AS5,AY5,AZ5),"Record midpoint",IF(AS5=MIN(AR5,AS5,AY5,AZ5),"National avg",IF(AY5=MIN(AR5,AS5,AY5,AZ5),"Prior award","ALJ")))) | BB5: =IF(OR(K5="",AA5=""),"",(K5-AA5)/30.4375) | BC5: =IF(OR(AF5="",AB5=""),"",AF5-AB5) | BD5: =IF(OR(O5="",N5=""),"",O5-N5) | BE5: =IF(K5="","",IF(K5<DATE(2022,1,1),"Pre (2019-21)",IF(K5<DATE(2023,1,1),"Transition (2022)","Post (2023-)")))
A6: P04 | AP6: =IF(COUNT(O6,R6:T6)=0,"",AVERAGE(O6,R6:T6)) | AQ6: =IF(OR(X6="",O6="",S6="",O6=S6),"",(X6-S6)/(O6-S6)) | AR6: =IF(OR(X6="",AP6=""),"",ABS(X6-AP6)) | AS6: =IF(OR(X6="",AE6=""),"",ABS(X6-AE6)) | AT6: =IF(OR(AR6="",AS6=""),"",IF(AS6<AR6,"National avg",IF(AR6<AS6,"Record midpoint","Tie"))) | AU6: =IF(OR(X6="",Z6=""),"",X6-Z6) | AV6: =IF(OR(X6="",AF6=""),"",X6-AF6) | AW6: =IF(X6="","",X6+IF(Y6="",0,Y6)/10000) | AX6: =IF(OR(X6="",V6="",W6="",W6=V6),"",(X6-V6)/(W6-V6)) | AY6: =IF(OR(X6="",Z6=""),"",ABS(X6-Z6)) | AZ6: =IF(OR(X6="",U6=""),"",ABS(X6-U6)) | BA6: =IF(COUNT(AR6,AS6,AY6,AZ6)<2,"",IF(AR6=MIN(AR6,AS6,AY6,AZ6),"Record midpoint",IF(AS6=MIN(AR6,AS6,AY6,AZ6),"National avg",IF(AY6=MIN(AR6,AS6,AY6,AZ6),"Prior award","ALJ")))) | BB6: =IF(OR(K6="",AA6=""),"",(K6-AA6)/30.4375) | BC6: =IF(OR(AF6="",AB6=""),"",AF6-AB6) | BD6: =IF(OR(O6="",N6=""),"",O6-N6) | BE6: =IF(K6="","",IF(K6<DATE(2022,1,1),"Pre (2019-21)",IF(K6<DATE(2023,1,1),"Transition (2022)","Post (2023-)")))
A7: P05 | AP7: =IF(COUNT(O7,R7:T7)=0,"",AVERAGE(O7,R7:T7)) | AQ7: =IF(OR(X7="",O7="",S7="",O7=S7),"",(X7-S7)/(O7-S7)) | AR7: =IF(OR(X7="",AP7=""),"",ABS(X7-AP7)) | AS7: =IF(OR(X7="",AE7=""),"",ABS(X7-AE7)) | AT7: =IF(OR(AR7="",AS7=""),"",IF(AS7<AR7,"National avg",IF(AR7<AS7,"Record midpoint","Tie"))) | AU7: =IF(OR(X7="",Z7=""),"",X7-Z7) | AV7: =IF(OR(X7="",AF7=""),"",X7-AF7) | AW7: =IF(X7="","",X7+IF(Y7="",0,Y7)/10000) | AX7: =IF(OR(X7="",V7="",W7="",W7=V7),"",(X7-V7)/(W7-V7)) | AY7: =IF(OR(X7="",Z7=""),"",ABS(X7-Z7)) | AZ7: =IF(OR(X7="",U7=""),"",ABS(X7-U7)) | BA7: =IF(COUNT(AR7,AS7,AY7,AZ7)<2,"",IF(AR7=MIN(AR7,AS7,AY7,AZ7),"Record midpoint",IF(AS7=MIN(AR7,AS7,AY7,AZ7),"National avg",IF(AY7=MIN(AR7,AS7,AY7,AZ7),"Prior award","ALJ")))) | BB7: =IF(OR(K7="",AA7=""),"",(K7-AA7)/30.4375) | BC7: =IF(OR(AF7="",AB7=""),"",AF7-AB7) | BD7: =IF(OR(O7="",N7=""),"",O7-N7) | BE7: =IF(K7="","",IF(K7<DATE(2022,1,1),"Pre (2019-21)",IF(K7<DATE(2023,1,1),"Transition (2022)","Post (2023-)")))
A8: P06 | AP8: =IF(COUNT(O8,R8:T8)=0,"",AVERAGE(O8,R8:T8)) | AQ8: =IF(OR(X8="",O8="",S8="",O8=S8),"",(X8-S8)/(O8-S8)) | AR8: =IF(OR(X8="",AP8=""),"",ABS(X8-AP8)) | AS8: =IF(OR(X8="",AE8=""),"",ABS(X8-AE8)) | AT8: =IF(OR(AR8="",AS8=""),"",IF(AS8<AR8,"National avg",IF(AR8<AS8,"Record midpoint","Tie"))) | AU8: =IF(OR(X8="",Z8=""),"",X8-Z8) | AV8: =IF(OR(X8="",AF8=""),"",X8-AF8) | AW8: =IF(X8="","",X8+IF(Y8="",0,Y8)/10000) | AX8: =IF(OR(X8="",V8="",W8="",W8=V8),"",(X8-V8)/(W8-V8)) | AY8: =IF(OR(X8="",Z8=""),"",ABS(X8-Z8)) | AZ8: =IF(OR(X8="",U8=""),"",ABS(X8-U8)) | BA8: =IF(COUNT(AR8,AS8,AY8,AZ8)<2,"",IF(AR8=MIN(AR8,AS8,AY8,AZ8),"Record midpoint",IF(AS8=MIN(AR8,AS8,AY8,AZ8),"National avg",IF(AY8=MIN(AR8,AS8,AY8,AZ8),"Prior award","ALJ")))) | BB8: =IF(OR(K8="",AA8=""),"",(K8-AA8)/30.4375) | BC8: =IF(OR(AF8="",AB8=""),"",AF8-AB8) | BD8: =IF(OR(O8="",N8=""),"",O8-N8) | BE8: =IF(K8="","",IF(K8<DATE(2022,1,1),"Pre (2019-21)",IF(K8<DATE(2023,1,1),"Transition (2022)","Post (2023-)")))
A9: P07 | AP9: =IF(COUNT(O9,R9:T9)=0,"",AVERAGE(O9,R9:T9)) | AQ9: =IF(OR(X9="",O9="",S9="",O9=S9),"",(X9-S9)/(O9-S9)) | AR9: =IF(OR(X9="",AP9=""),"",ABS(X9-AP9)) | AS9: =IF(OR(X9="",AE9=""),"",ABS(X9-AE9)) | AT9: =IF(OR(AR9="",AS9=""),"",IF(AS9<AR9,"National avg",IF(AR9<AS9,"Record midpoint","Tie"))) | AU9: =IF(OR(X9="",Z9=""),"",X9-Z9) | AV9: =IF(OR(X9="",AF9=""),"",X9-AF9) | AW9: =IF(X9="","",X9+IF(Y9="",0,Y9)/10000) | AX9: =IF(OR(X9="",V9="",W9="",W9=V9),"",(X9-V9)/(W9-V9)) | AY9: =IF(OR(X9="",Z9=""),"",ABS(X9-Z9)) | AZ9: =IF(OR(X9="",U9=""),"",ABS(X9-U9)) | BA9: =IF(COUNT(AR9,AS9,AY9,AZ9)<2,"",IF(AR9=MIN(AR9,AS9,AY9,AZ9),"Record midpoint",IF(AS9=MIN(AR9,AS9,AY9,AZ9),"National avg",IF(AY9=MIN(AR9,AS9,AY9,AZ9),"Prior award","ALJ")))) | BB9: =IF(OR(K9="",AA9=""),"",(K9-AA9)/30.4375) | BC9: =IF(OR(AF9="",AB9=""),"",AF9-AB9) | BD9: =IF(OR(O9="",N9=""),"",O9-N9) | BE9: =IF(K9="","",IF(K9<DATE(2022,1,1),"Pre (2019-21)",IF(K9<DATE(2023,1,1),"Transition (2022)","Post (2023-)")))
A10: P08 | AP10: =IF(COUNT(O10,R10:T10)=0,"",AVERAGE(O10,R10:T10)) | AQ10: =IF(OR(X10="",O10="",S10="",O10=S10),"",(X10-S10)/(O10-S10)) | AR10: =IF(OR(X10="",AP10=""),"",ABS(X10-AP10)) | AS10: =IF(OR(X10="",AE10=""),"",ABS(X10-AE10)) | AT10: =IF(OR(AR10="",AS10=""),"",IF(AS10<AR10,"National avg",IF(AR10<AS10,"Record midpoint","Tie"))) | AU10: =IF(OR(X10="",Z10=""),"",X10-Z10) | AV10: =IF(OR(X10="",AF10=""),"",X10-AF10) | AW10: =IF(X10="","",X10+IF(Y10="",0,Y10)/10000) | AX10: =IF(OR(X10="",V10="",W10="",W10=V10),"",(X10-V10)/(W10-V10)) | AY10: =IF(OR(X10="",Z10=""),"",ABS(X10-Z10)) | AZ10: =IF(OR(X10="",U10=""),"",ABS(X10-U10)) | BA10: =IF(COUNT(AR10,AS10,AY10,AZ10)<2,"",IF(AR10=MIN(AR10,AS10,AY10,AZ10),"Record midpoint",IF(AS10=MIN(AR10,AS10,AY10,AZ10),"National avg",IF(AY10=MIN(AR10,AS10,AY10,AZ10),"Prior award","ALJ")))) | BB10: =IF(OR(K10="",AA10=""),"",(K10-AA10)/30.4375) | BC10: =IF(OR(AF10="",AB10=""),"",AF10-AB10) | BD10: =IF(OR(O10="",N10=""),"",O10-N10) | BE10: =IF(K10="","",IF(K10<DATE(2022,1,1),"Pre (2019-21)",IF(K10<DATE(2023,1,1),"Transition (2022)","Post (2023-)")))
A11: P09 | AP11: =IF(COUNT(O11,R11:T11)=0,"",AVERAGE(O11,R11:T11)) | AQ11: =IF(OR(X11="",O11="",S11="",O11=S11),"",(X11-S11)/(O11-S11)) | AR11: =IF(OR(X11="",AP11=""),"",ABS(X11-AP11)) | AS11: =IF(OR(X11="",AE11=""),"",ABS(X11-AE11)) | AT11: =IF(OR(AR11="",AS11=""),"",IF(AS11<AR11,"National avg",IF(AR11<AS11,"Record midpoint","Tie"))) | AU11: =IF(OR(X11="",Z11=""),"",X11-Z11) | AV11: =IF(OR(X11="",AF11=""),"",X11-AF11) | AW11: =IF(X11="","",X11+IF(Y11="",0,Y11)/10000) | AX11: =IF(OR(X11="",V11="",W11="",W11=V11),"",(X11-V11)/(W11-V11)) | AY11: =IF(OR(X11="",Z11=""),"",ABS(X11-Z11)) | AZ11: =IF(OR(X11="",U11=""),"",ABS(X11-U11)) | BA11: =IF(COUNT(AR11,AS11,AY11,AZ11)<2,"",IF(AR11=MIN(AR11,AS11,AY11,AZ11),"Record midpoint",IF(AS11=MIN(AR11,AS11,AY11,AZ11),"National avg",IF(AY11=MIN(AR11,AS11,AY11,AZ11),"Prior award","ALJ")))) | BB11: =IF(OR(K11="",AA11=""),"",(K11-AA11)/30.4375) | BC11: =IF(OR(AF11="",AB11=""),"",AF11-AB11) | BD11: =IF(OR(O11="",N11=""),"",O11-N11) | BE11: =IF(K11="","",IF(K11<DATE(2022,1,1),"Pre (2019-21)",IF(K11<DATE(2023,1,1),"Transition (2022)","Post (2023-)")))
A12: P10 | AP12: =IF(COUNT(O12,R12:T12)=0,"",AVERAGE(O12,R12:T12)) | AQ12: =IF(OR(X12="",O12="",S12="",O12=S12),"",(X12-S12)/(O12-S12)) | AR12: =IF(OR(X12="",AP12=""),"",ABS(X12-AP12)) | AS12: =IF(OR(X12="",AE12=""),"",ABS(X12-AE12)) | AT12: =IF(OR(AR12="",AS12=""),"",IF(AS12<AR12,"National avg",IF(AR12<AS12,"Record midpoint","Tie"))) | AU12: =IF(OR(X12="",Z12=""),"",X12-Z12) | AV12: =IF(OR(X12="",AF12=""),"",X12-AF12) | AW12: =IF(X12="","",X12+IF(Y12="",0,Y12)/10000) | AX12: =IF(OR(X12="",V12="",W12="",W12=V12),"",(X12-V12)/(W12-V12)) | AY12: =IF(OR(X12="",Z12=""),"",ABS(X12-Z12)) | AZ12: =IF(OR(X12="",U12=""),"",ABS(X12-U12)) | BA12: =IF(COUNT(AR12,AS12,AY12,AZ12)<2,"",IF(AR12=MIN(AR12,AS12,AY12,AZ12),"Record midpoint",IF(AS12=MIN(AR12,AS12,AY12,AZ12),"National avg",IF(AY12=MIN(AR12,AS12,AY12,AZ12),"Prior award","ALJ")))) | BB12: =IF(OR(K12="",AA12=""),"",(K12-AA12)/30.4375) | BC12: =IF(OR(AF12="",AB12=""),"",AF12-AB12) | BD12: =IF(OR(O12="",N12=""),"",O12-N12) | BE12: =IF(K12="","",IF(K12<DATE(2022,1,1),"Pre (2019-21)",IF(K12<DATE(2023,1,1),"Transition (2022)","Post (2023-)")))
A13: P11 | AP13: =IF(COUNT(O13,R13:T13)=0,"",AVERAGE(O13,R13:T13)) | AQ13: =IF(OR(X13="",O13="",S13="",O13=S13),"",(X13-S13)/(O13-S13)) | AR13: =IF(OR(X13="",AP13=""),"",ABS(X13-AP13)) | AS13: =IF(OR(X13="",AE13=""),"",ABS(X13-AE13)) | AT13: =IF(OR(AR13="",AS13=""),"",IF(AS13<AR13,"National avg",IF(AR13<AS13,"Record midpoint","Tie"))) | AU13: =IF(OR(X13="",Z13=""),"",X13-Z13) | AV13: =IF(OR(X13="",AF13=""),"",X13-AF13) | AW13: =IF(X13="","",X13+IF(Y13="",0,Y13)/10000) | AX13: =IF(OR(X13="",V13="",W13="",W13=V13),"",(X13-V13)/(W13-V13)) | AY13: =IF(OR(X13="",Z13=""),"",ABS(X13-Z13)) | AZ13: =IF(OR(X13="",U13=""),"",ABS(X13-U13)) | BA13: =IF(COUNT(AR13,AS13,AY13,AZ13)<2,"",IF(AR13=MIN(AR13,AS13,AY13,AZ13),"Record midpoint",IF(AS13=MIN(AR13,AS13,AY13,AZ13),"National avg",IF(AY13=MIN(AR13,AS13,AY13,AZ13),"Prior award","ALJ")))) | BB13: =IF(OR(K13="",AA13=""),"",(K13-AA13)/30.4375) | BC13: =IF(OR(AF13="",AB13=""),"",AF13-AB13) | BD13: =IF(OR(O13="",N13=""),"",O13-N13) | BE13: =IF(K13="","",IF(K13<DATE(2022,1,1),"Pre (2019-21)",IF(K13<DATE(2023,1,1),"Transition (2022)","Post (2023-)")))
A14: P12 | AP14: =IF(COUNT(O14,R14:T14)=0,"",AVERAGE(O14,R14:T14)) | AQ14: =IF(OR(X14="",O14="",S14="",O14=S14),"",(X14-S14)/(O14-S14)) | AR14: =IF(OR(X14="",AP14=""),"",ABS(X14-AP14)) | AS14: =IF(OR(X14="",AE14=""),"",ABS(X14-AE14)) | AT14: =IF(OR(AR14="",AS14=""),"",IF(AS14<AR14,"National avg",IF(AR14<AS14,"Record midpoint","Tie"))) | AU14: =IF(OR(X14="",Z14=""),"",X14-Z14) | AV14: =IF(OR(X14="",AF14=""),"",X14-AF14) | AW14: =IF(X14="","",X14+IF(Y14="",0,Y14)/10000) | AX14: =IF(OR(X14="",V14="",W14="",W14=V14),"",(X14-V14)/(W14-V14)) | AY14: =IF(OR(X14="",Z14=""),"",ABS(X14-Z14)) | AZ14: =IF(OR(X14="",U14=""),"",ABS(X14-U14)) | BA14: =IF(COUNT(AR14,AS14,AY14,AZ14)<2,"",IF(AR14=MIN(AR14,AS14,AY14,AZ14),"Record midpoint",IF(AS14=MIN(AR14,AS14,AY14,AZ14),"National avg",IF(AY14=MIN(AR14,AS14,AY14,AZ14),"Prior award","ALJ")))) | BB14: =IF(OR(K14="",AA14=""),"",(K14-AA14)/30.4375) | BC14: =IF(OR(AF14="",AB14=""),"",AF14-AB14) | BD14: =IF(OR(O14="",N14=""),"",O14-N14) | BE14: =IF(K14="","",IF(K14<DATE(2022,1,1),"Pre (2019-21)",IF(K14<DATE(2023,1,1),"Transition (2022)","Post (2023-)")))
... A17: P15 | AP17: =IF(COUNT(O17,R17:T17)=0,"",AVERAGE(O17,R17:T17)) | AQ17: =IF(OR(X17="",O17="",S17="",O17=S17),"",(X17-S17)/(O17-S17)) | AR17: =IF(OR(X17="",AP17=""),"",ABS(X17-AP17)) | AS17: =IF(OR(X17="",AE17=""),"",ABS(X17-AE17)) | AT17: =IF(OR(AR17="",AS17=""),"",IF(AS17<AR17,"National avg",IF(AR17<AS17,"Record midpoint","Tie"))) | AU17: =IF(OR(X17="",Z17=""),"",X17-Z17) | AV17: =IF(OR(X17="",AF17=""),"",X17-AF17) | AW17: =IF(X17="","",X17+IF(Y17="",0,Y17)/10000) | AX17: =IF(OR(X17="",V17="",W17="",W17=V17),"",(X17-V17)/(W17-V17)) | AY17: =IF(OR(X17="",Z17=""),"",ABS(X17-Z17)) | AZ17: =IF(OR(X17="",U17=""),"",ABS(X17-U17)) | BA17: =IF(COUNT(AR17,AS17,AY17,AZ17)<2,"",IF(AR17=MIN(AR17,AS17,AY17,AZ17),"Record midpoint",IF(AS17=MIN(AR17,AS17,AY17,AZ17),"National avg",IF(AY17=MIN(AR17,AS17,AY17,AZ17),"Prior award","ALJ")))) | BB17: =IF(OR(K17="",AA17=""),"",(K17-AA17)/30.4375) | BC17: =IF(OR(AF17="",AB17=""),"",AF17-AB17) | BD17: =IF(OR(O17="",N17=""),"",O17-N17) | BE17: =IF(K17="","",IF(K17<DATE(2022,1,1),"Pre (2019-21)",IF(K17<DATE(2023,1,1),"Transition (2022)","Post (2023-)")))

Sheet Passages
A1: passage_id | B1: case_id | C1: page_para | D1: section | E1: excerpt | F1: MKT | G1: method | H1: PEER | I1: OWN | J1: GRAD | K1: LAW | L1: CAP | M1: RISK | N1: AFF | O1: PERF | P1: DEF | Q1: CONC | R1: primary_code | S1: stance | T1: coder | U1: notes
A2: EX-01-001 | B2: EX-01 | C2: p.?/¶? | D2: Commission analysis | E2: ILLUSTRATIVE ONLY — constructed text, not from the order. Replace with the actual paragraph: “Having considered the record as a whole, we find that a return on equity of 9.5 percent is just and reasonable.” | F2: 0 | G2: n.a. | H2: 0 | I2: 0 | J2: 0 | K2: 0 | L2: 0 | M2: 0 | N2: 0 | O2: 0 | P2: 0 | Q2: 1 | R2: CONC | S2: Relied on | T2: EXAMPLE | U2: Shows format. CONC here would be provisional until the full analysis is read (Rule 6).

Sheet Case_Codes
A1: case_id | B1: n_commission_passages | C1: n_MKT | D1: n_PEER | E1: n_OWN | F1: n_GRAD | G1: n_LAW | H1: n_CAP | I1: n_RISK | J1: n_AFF | K1: n_PERF | L1: n_DEF | M1: n_CONC | N1: anchor_present | O1: market_present | P1: anchor_share
A2: =Cases!A2 -> EX-01 | B2: =COUNTIFS(Passages!$B$2:$B$400,$A2,Passages!$D$2:$D$400,"Commission analysis") -> 1 | C2: =COUNTIFS(Passages!$B$2:$B$400,$A2,Passages!$D$2:$D$400,"Commission analysis",Passages!$F$2:$F$400,1) -> 0 | D2: =COUNTIFS(Passages!$B$2:$B$400,$A2,Passages!$D$2:$D$400,"Commission analysis",Passages!$H$2:$H$400,1) -> 0 | E2: =COUNTIFS(Passages!$B$2:$B$400,$A2,Passages!$D$2:$D$400,"Commission analysis",Passages!$I$2:$I$400,1) -> 0 | F2: =COUNTIFS(Passages!$B$2:$B$400,$A2,Passages!$D$2:$D$400,"Commission analysis",Passages!$J$2:$J$400,1) -> 0 | G2: =COUNTIFS(Passages!$B$2:$B$400,$A2,Passages!$D$2:$D$400,"Commission analysis",Passages!$K$2:$K$400,1) -> 0 | H2: =COUNTIFS(Passages!$B$2:$B$400,$A2,Passages!$D$2:$D$400,"Commission analysis",Passages!$L$2:$L$400,1) -> 0 | I2: =COUNTIFS(Passages!$B$2:$B$400,$A2,Passages!$D$2:$D$400,"Commission analysis",Passages!$M$2:$M$400,1) -> 0 | J2: =COUNTIFS(Passages!$B$2:$B$400,$A2,Passages!$D$2:$D$400,"Commission analysis",Passages!$N$2:$N$400,1) -> 0 | K2: =COUNTIFS(Passages!$B$2:$B$400,$A2,Passages!$D$2:$D$400,"Commission analysis",Passages!$O$2:$O$400,1) -> 0 | L2: =COUNTIFS(Passages!$B$2:$B$400,$A2,Passages!$D$2:$D$400,"Commission analysis",Passages!$P$2:$P$400,1) -> 0 | M2: =COUNTIFS(Passages!$B$2:$B$400,$A2,Passages!$D$2:$D$400,"Commission analysis",Passages!$Q$2:$Q$400,1) -> 1 | N2: =IF(B2=0,"",IF((D2+E2+F2)>0,1,0)) -> 0 | O2: =IF(B2=0,"",IF(C2>0,1,0)) -> 0 | P2: =IF((D2+E2+F2)+C2=0,"",(D2+E2+F2)/((D2+E2+F2)+C2))
A3: =Cases!A3 -> P01 | B3: =COUNTIFS(Passages!$B$2:$B$400,$A3,Passages!$D$2:$D$400,"Commission analysis") -> 0 | C3: =COUNTIFS(Passages!$B$2:$B$400,$A3,Passages!$D$2:$D$400,"Commission analysis",Passages!$F$2:$F$400,1) -> 0 | D3: =COUNTIFS(Passages!$B$2:$B$400,$A3,Passages!$D$2:$D$400,"Commission analysis",Passages!$H$2:$H$400,1) -> 0 | E3: =COUNTIFS(Passages!$B$2:$B$400,$A3,Passages!$D$2:$D$400,"Commission analysis",Passages!$I$2:$I$400,1) -> 0 | F3: =COUNTIFS(Passages!$B$2:$B$400,$A3,Passages!$D$2:$D$400,"Commission analysis",Passages!$J$2:$J$400,1) -> 0 | G3: =COUNTIFS(Passages!$B$2:$B$400,$A3,Passages!$D$2:$D$400,"Commission analysis",Passages!$K$2:$K$400,1) -> 0 | H3: =COUNTIFS(Passages!$B$2:$B$400,$A3,Passages!$D$2:$D$400,"Commission analysis",Passages!$L$2:$L$400,1) -> 0 | I3: =COUNTIFS(Passages!$B$2:$B$400,$A3,Passages!$D$2:$D$400,"Commission analysis",Passages!$M$2:$M$400,1) -> 0 | J3: =COUNTIFS(Passages!$B$2:$B$400,$A3,Passages!$D$2:$D$400,"Commission analysis",Passages!$N$2:$N$400,1) -> 0 | K3: =COUNTIFS(Passages!$B$2:$B$400,$A3,Passages!$D$2:$D$400,"Commission analysis",Passages!$O$2:$O$400,1) -> 0 | L3: =COUNTIFS(Passages!$B$2:$B$400,$A3,Passages!$D$2:$D$400,"Commission analysis",Passages!$P$2:$P$400,1) -> 0 | M3: =COUNTIFS(Passages!$B$2:$B$400,$A3,Passages!$D$2:$D$400,"Commission analysis",Passages!$Q$2:$Q$400,1) -> 0 | N3: =IF(B3=0,"",IF((D3+E3+F3)>0,1,0)) | O3: =IF(B3=0,"",IF(C3>0,1,0)) | P3: =IF((D3+E3+F3)+C3=0,"",(D3+E3+F3)/((D3+E3+F3)+C3))
A4: =Cases!A4 -> P02 | B4: =COUNTIFS(Passages!$B$2:$B$400,$A4,Passages!$D$2:$D$400,"Commission analysis") -> 0 | C4: =COUNTIFS(Passages!$B$2:$B$400,$A4,Passages!$D$2:$D$400,"Commission analysis",Passages!$F$2:$F$400,1) -> 0 | D4: =COUNTIFS(Passages!$B$2:$B$400,$A4,Passages!$D$2:$D$400,"Commission analysis",Passages!$H$2:$H$400,1) -> 0 | E4: =COUNTIFS(Passages!$B$2:$B$400,$A4,Passages!$D$2:$D$400,"Commission analysis",Passages!$I$2:$I$400,1) -> 0 | F4: =COUNTIFS(Passages!$B$2:$B$400,$A4,Passages!$D$2:$D$400,"Commission analysis",Passages!$J$2:$J$400,1) -> 0 | G4: =COUNTIFS(Passages!$B$2:$B$400,$A4,Passages!$D$2:$D$400,"Commission analysis",Passages!$K$2:$K$400,1) -> 0 | H4: =COUNTIFS(Passages!$B$2:$B$400,$A4,Passages!$D$2:$D$400,"Commission analysis",Passages!$L$2:$L$400,1) -> 0 | I4: =COUNTIFS(Passages!$B$2:$B$400,$A4,Passages!$D$2:$D$400,"Commission analysis",Passages!$M$2:$M$400,1) -> 0 | J4: =COUNTIFS(Passages!$B$2:$B$400,$A4,Passages!$D$2:$D$400,"Commission analysis",Passages!$N$2:$N$400,1) -> 0 | K4: =COUNTIFS(Passages!$B$2:$B$400,$A4,Passages!$D$2:$D$400,"Commission analysis",Passages!$O$2:$O$400,1) -> 0 | L4: =COUNTIFS(Passages!$B$2:$B$400,$A4,Passages!$D$2:$D$400,"Commission analysis",Passages!$P$2:$P$400,1) -> 0 | M4: =COUNTIFS(Passages!$B$2:$B$400,$A4,Passages!$D$2:$D$400,"Commission analysis",Passages!$Q$2:$Q$400,1) -> 0 | N4: =IF(B4=0,"",IF((D4+E4+F4)>0,1,0)) | O4: =IF(B4=0,"",IF(C4>0,1,0)) | P4: =IF((D4+E4+F4)+C4=0,"",(D4+E4+F4)/((D4+E4+F4)+C4))
A5: =Cases!A5 -> P03 | B5: =COUNTIFS(Passages!$B$2:$B$400,$A5,Passages!$D$2:$D$400,"Commission analysis") -> 0 | C5: =COUNTIFS(Passages!$B$2:$B$400,$A5,Passages!$D$2:$D$400,"Commission analysis",Passages!$F$2:$F$400,1) -> 0 | D5: =COUNTIFS(Passages!$B$2:$B$400,$A5,Passages!$D$2:$D$400,"Commission analysis",Passages!$H$2:$H$400,1) -> 0 | E5: =COUNTIFS(Passages!$B$2:$B$400,$A5,Passages!$D$2:$D$400,"Commission analysis",Passages!$I$2:$I$400,1) -> 0 | F5: =COUNTIFS(Passages!$B$2:$B$400,$A5,Passages!$D$2:$D$400,"Commission analysis",Passages!$J$2:$J$400,1) -> 0 | G5: =COUNTIFS(Passages!$B$2:$B$400,$A5,Passages!$D$2:$D$400,"Commission analysis",Passages!$K$2:$K$400,1) -> 0 | H5: =COUNTIFS(Passages!$B$2:$B$400,$A5,Passages!$D$2:$D$400,"Commission analysis",Passages!$L$2:$L$400,1) -> 0 | I5: =COUNTIFS(Passages!$B$2:$B$400,$A5,Passages!$D$2:$D$400,"Commission analysis",Passages!$M$2:$M$400,1) -> 0 | J5: =COUNTIFS(Passages!$B$2:$B$400,$A5,Passages!$D$2:$D$400,"Commission analysis",Passages!$N$2:$N$400,1) -> 0 | K5: =COUNTIFS(Passages!$B$2:$B$400,$A5,Passages!$D$2:$D$400,"Commission analysis",Passages!$O$2:$O$400,1) -> 0 | L5: =COUNTIFS(Passages!$B$2:$B$400,$A5,Passages!$D$2:$D$400,"Commission analysis",Passages!$P$2:$P$400,1) -> 0 | M5: =COUNTIFS(Passages!$B$2:$B$400,$A5,Passages!$D$2:$D$400,"Commission analysis",Passages!$Q$2:$Q$400,1) -> 0 | N5: =IF(B5=0,"",IF((D5+E5+F5)>0,1,0)) | O5: =IF(B5=0,"",IF(C5>0,1,0)) | P5: =IF((D5+E5+F5)+C5=0,"",(D5+E5+F5)/((D5+E5+F5)+C5))
A6: =Cases!A6 -> P04 | B6: =COUNTIFS(Passages!$B$2:$B$400,$A6,Passages!$D$2:$D$400,"Commission analysis") -> 0 | C6: =COUNTIFS(Passages!$B$2:$B$400,$A6,Passages!$D$2:$D$400,"Commission analysis",Passages!$F$2:$F$400,1) -> 0 | D6: =COUNTIFS(Passages!$B$2:$B$400,$A6,Passages!$D$2:$D$400,"Commission analysis",Passages!$H$2:$H$400,1) -> 0 | E6: =COUNTIFS(Passages!$B$2:$B$400,$A6,Passages!$D$2:$D$400,"Commission analysis",Passages!$I$2:$I$400,1) -> 0 | F6: =COUNTIFS(Passages!$B$2:$B$400,$A6,Passages!$D$2:$D$400,"Commission analysis",Passages!$J$2:$J$400,1) -> 0 | G6: =COUNTIFS(Passages!$B$2:$B$400,$A6,Passages!$D$2:$D$400,"Commission analysis",Passages!$K$2:$K$400,1) -> 0 | H6: =COUNTIFS(Passages!$B$2:$B$400,$A6,Passages!$D$2:$D$400,"Commission analysis",Passages!$L$2:$L$400,1) -> 0 | I6: =COUNTIFS(Passages!$B$2:$B$400,$A6,Passages!$D$2:$D$400,"Commission analysis",Passages!$M$2:$M$400,1) -> 0 | J6: =COUNTIFS(Passages!$B$2:$B$400,$A6,Passages!$D$2:$D$400,"Commission analysis",Passages!$N$2:$N$400,1) -> 0 | K6: =COUNTIFS(Passages!$B$2:$B$400,$A6,Passages!$D$2:$D$400,"Commission analysis",Passages!$O$2:$O$400,1) -> 0 | L6: =COUNTIFS(Passages!$B$2:$B$400,$A6,Passages!$D$2:$D$400,"Commission analysis",Passages!$P$2:$P$400,1) -> 0 | M6: =COUNTIFS(Passages!$B$2:$B$400,$A6,Passages!$D$2:$D$400,"Commission analysis",Passages!$Q$2:$Q$400,1) -> 0 | N6: =IF(B6=0,"",IF((D6+E6+F6)>0,1,0)) | O6: =IF(B6=0,"",IF(C6>0,1,0)) | P6: =IF((D6+E6+F6)+C6=0,"",(D6+E6+F6)/((D6+E6+F6)+C6))
A7: =Cases!A7 -> P05 | B7: =COUNTIFS(Passages!$B$2:$B$400,$A7,Passages!$D$2:$D$400,"Commission analysis") -> 0 | C7: =COUNTIFS(Passages!$B$2:$B$400,$A7,Passages!$D$2:$D$400,"Commission analysis",Passages!$F$2:$F$400,1) -> 0 | D7: =COUNTIFS(Passages!$B$2:$B$400,$A7,Passages!$D$2:$D$400,"Commission analysis",Passages!$H$2:$H$400,1) -> 0 | E7: =COUNTIFS(Passages!$B$2:$B$400,$A7,Passages!$D$2:$D$400,"Commission analysis",Passages!$I$2:$I$400,1) -> 0 | F7: =COUNTIFS(Passages!$B$2:$B$400,$A7,Passages!$D$2:$D$400,"Commission analysis",Passages!$J$2:$J$400,1) -> 0 | G7: =COUNTIFS(Passages!$B$2:$B$400,$A7,Passages!$D$2:$D$400,"Commission analysis",Passages!$K$2:$K$400,1) -> 0 | H7: =COUNTIFS(Passages!$B$2:$B$400,$A7,Passages!$D$2:$D$400,"Commission analysis",Passages!$L$2:$L$400,1) -> 0 | I7: =COUNTIFS(Passages!$B$2:$B$400,$A7,Passages!$D$2:$D$400,"Commission analysis",Passages!$M$2:$M$400,1) -> 0 | J7: =COUNTIFS(Passages!$B$2:$B$400,$A7,Passages!$D$2:$D$400,"Commission analysis",Passages!$N$2:$N$400,1) -> 0 | K7: =COUNTIFS(Passages!$B$2:$B$400,$A7,Passages!$D$2:$D$400,"Commission analysis",Passages!$O$2:$O$400,1) -> 0 | L7: =COUNTIFS(Passages!$B$2:$B$400,$A7,Passages!$D$2:$D$400,"Commission analysis",Passages!$P$2:$P$400,1) -> 0 | M7: =COUNTIFS(Passages!$B$2:$B$400,$A7,Passages!$D$2:$D$400,"Commission analysis",Passages!$Q$2:$Q$400,1) -> 0 | N7: =IF(B7=0,"",IF((D7+E7+F7)>0,1,0)) | O7: =IF(B7=0,"",IF(C7>0,1,0)) | P7: =IF((D7+E7+F7)+C7=0,"",(D7+E7+F7)/((D7+E7+F7)+C7))
A8: =Cases!A8 -> P06 | B8: =COUNTIFS(Passages!$B$2:$B$400,$A8,Passages!$D$2:$D$400,"Commission analysis") -> 0 | C8: =COUNTIFS(Passages!$B$2:$B$400,$A8,Passages!$D$2:$D$400,"Commission analysis",Passages!$F$2:$F$400,1) -> 0 | D8: =COUNTIFS(Passages!$B$2:$B$400,$A8,Passages!$D$2:$D$400,"Commission analysis",Passages!$H$2:$H$400,1) -> 0 | E8: =COUNTIFS(Passages!$B$2:$B$400,$A8,Passages!$D$2:$D$400,"Commission analysis",Passages!$I$2:$I$400,1) -> 0 | F8: =COUNTIFS(Passages!$B$2:$B$400,$A8,Passages!$D$2:$D$400,"Commission analysis",Passages!$J$2:$J$400,1) -> 0 | G8: =COUNTIFS(Passages!$B$2:$B$400,$A8,Passages!$D$2:$D$400,"Commission analysis",Passages!$K$2:$K$400,1) -> 0 | H8: =COUNTIFS(Passages!$B$2:$B$400,$A8,Passages!$D$2:$D$400,"Commission analysis",Passages!$L$2:$L$400,1) -> 0 | I8: =COUNTIFS(Passages!$B$2:$B$400,$A8,Passages!$D$2:$D$400,"Commission analysis",Passages!$M$2:$M$400,1) -> 0 | J8: =COUNTIFS(Passages!$B$2:$B$400,$A8,Passages!$D$2:$D$400,"Commission analysis",Passages!$N$2:$N$400,1) -> 0 | K8: =COUNTIFS(Passages!$B$2:$B$400,$A8,Passages!$D$2:$D$400,"Commission analysis",Passages!$O$2:$O$400,1) -> 0 | L8: =COUNTIFS(Passages!$B$2:$B$400,$A8,Passages!$D$2:$D$400,"Commission analysis",Passages!$P$2:$P$400,1) -> 0 | M8: =COUNTIFS(Passages!$B$2:$B$400,$A8,Passages!$D$2:$D$400,"Commission analysis",Passages!$Q$2:$Q$400,1) -> 0 | N8: =IF(B8=0,"",IF((D8+E8+F8)>0,1,0)) | O8: =IF(B8=0,"",IF(C8>0,1,0)) | P8: =IF((D8+E8+F8)+C8=0,"",(D8+E8+F8)/((D8+E8+F8)+C8))
A9: =Cases!A9 -> P07 | B9: =COUNTIFS(Passages!$B$2:$B$400,$A9,Passages!$D$2:$D$400,"Commission analysis") -> 0 | C9: =COUNTIFS(Passages!$B$2:$B$400,$A9,Passages!$D$2:$D$400,"Commission analysis",Passages!$F$2:$F$400,1) -> 0 | D9: =COUNTIFS(Passages!$B$2:$B$400,$A9,Passages!$D$2:$D$400,"Commission analysis",Passages!$H$2:$H$400,1) -> 0 | E9: =COUNTIFS(Passages!$B$2:$B$400,$A9,Passages!$D$2:$D$400,"Commission analysis",Passages!$I$2:$I$400,1) -> 0 | F9: =COUNTIFS(Passages!$B$2:$B$400,$A9,Passages!$D$2:$D$400,"Commission analysis",Passages!$J$2:$J$400,1) -> 0 | G9: =COUNTIFS(Passages!$B$2:$B$400,$A9,Passages!$D$2:$D$400,"Commission analysis",Passages!$K$2:$K$400,1) -> 0 | H9: =COUNTIFS(Passages!$B$2:$B$400,$A9,Passages!$D$2:$D$400,"Commission analysis",Passages!$L$2:$L$400,1) -> 0 | I9: =COUNTIFS(Passages!$B$2:$B$400,$A9,Passages!$D$2:$D$400,"Commission analysis",Passages!$M$2:$M$400,1) -> 0 | J9: =COUNTIFS(Passages!$B$2:$B$400,$A9,Passages!$D$2:$D$400,"Commission analysis",Passages!$N$2:$N$400,1) -> 0 | K9: =COUNTIFS(Passages!$B$2:$B$400,$A9,Passages!$D$2:$D$400,"Commission analysis",Passages!$O$2:$O$400,1) -> 0 | L9: =COUNTIFS(Passages!$B$2:$B$400,$A9,Passages!$D$2:$D$400,"Commission analysis",Passages!$P$2:$P$400,1) -> 0 | M9: =COUNTIFS(Passages!$B$2:$B$400,$A9,Passages!$D$2:$D$400,"Commission analysis",Passages!$Q$2:$Q$400,1) -> 0 | N9: =IF(B9=0,"",IF((D9+E9+F9)>0,1,0)) | O9: =IF(B9=0,"",IF(C9>0,1,0)) | P9: =IF((D9+E9+F9)+C9=0,"",(D9+E9+F9)/((D9+E9+F9)+C9))
A10: =Cases!A10 -> P08 | B10: =COUNTIFS(Passages!$B$2:$B$400,$A10,Passages!$D$2:$D$400,"Commission analysis") -> 0 | C10: =COUNTIFS(Passages!$B$2:$B$400,$A10,Passages!$D$2:$D$400,"Commission analysis",Passages!$F$2:$F$400,1) -> 0 | D10: =COUNTIFS(Passages!$B$2:$B$400,$A10,Passages!$D$2:$D$400,"Commission analysis",Passages!$H$2:$H$400,1) -> 0 | E10: =COUNTIFS(Passages!$B$2:$B$400,$A10,Passages!$D$2:$D$400,"Commission analysis",Passages!$I$2:$I$400,1) -> 0 | F10: =COUNTIFS(Passages!$B$2:$B$400,$A10,Passages!$D$2:$D$400,"Commission analysis",Passages!$J$2:$J$400,1) -> 0 | G10: =COUNTIFS(Passages!$B$2:$B$400,$A10,Passages!$D$2:$D$400,"Commission analysis",Passages!$K$2:$K$400,1) -> 0 | H10: =COUNTIFS(Passages!$B$2:$B$400,$A10,Passages!$D$2:$D$400,"Commission analysis",Passages!$L$2:$L$400,1) -> 0 | I10: =COUNTIFS(Passages!$B$2:$B$400,$A10,Passages!$D$2:$D$400,"Commission analysis",Passages!$M$2:$M$400,1) -> 0 | J10: =COUNTIFS(Passages!$B$2:$B$400,$A10,Passages!$D$2:$D$400,"Commission analysis",Passages!$N$2:$N$400,1) -> 0 | K10: =COUNTIFS(Passages!$B$2:$B$400,$A10,Passages!$D$2:$D$400,"Commission analysis",Passages!$O$2:$O$400,1) -> 0 | L10: =COUNTIFS(Passages!$B$2:$B$400,$A10,Passages!$D$2:$D$400,"Commission analysis",Passages!$P$2:$P$400,1) -> 0 | M10: =COUNTIFS(Passages!$B$2:$B$400,$A10,Passages!$D$2:$D$400,"Commission analysis",Passages!$Q$2:$Q$400,1) -> 0 | N10: =IF(B10=0,"",IF((D10+E10+F10)>0,1,0)) | O10: =IF(B10=0,"",IF(C10>0,1,0)) | P10: =IF((D10+E10+F10)+C10=0,"",(D10+E10+F10)/((D10+E10+F10)+C10))
A11: =Cases!A11 -> P09 | B11: =COUNTIFS(Passages!$B$2:$B$400,$A11,Passages!$D$2:$D$400,"Commission analysis") -> 0 | C11: =COUNTIFS(Passages!$B$2:$B$400,$A11,Passages!$D$2:$D$400,"Commission analysis",Passages!$F$2:$F$400,1) -> 0 | D11: =COUNTIFS(Passages!$B$2:$B$400,$A11,Passages!$D$2:$D$400,"Commission analysis",Passages!$H$2:$H$400,1) -> 0 | E11: =COUNTIFS(Passages!$B$2:$B$400,$A11,Passages!$D$2:$D$400,"Commission analysis",Passages!$I$2:$I$400,1) -> 0 | F11: =COUNTIFS(Passages!$B$2:$B$400,$A11,Passages!$D$2:$D$400,"Commission analysis",Passages!$J$2:$J$400,1) -> 0 | G11: =COUNTIFS(Passages!$B$2:$B$400,$A11,Passages!$D$2:$D$400,"Commission analysis",Passages!$K$2:$K$400,1) -> 0 | H11: =COUNTIFS(Passages!$B$2:$B$400,$A11,Passages!$D$2:$D$400,"Commission analysis",Passages!$L$2:$L$400,1) -> 0 | I11: =COUNTIFS(Passages!$B$2:$B$400,$A11,Passages!$D$2:$D$400,"Commission analysis",Passages!$M$2:$M$400,1) -> 0 | J11: =COUNTIFS(Passages!$B$2:$B$400,$A11,Passages!$D$2:$D$400,"Commission analysis",Passages!$N$2:$N$400,1) -> 0 | K11: =COUNTIFS(Passages!$B$2:$B$400,$A11,Passages!$D$2:$D$400,"Commission analysis",Passages!$O$2:$O$400,1) -> 0 | L11: =COUNTIFS(Passages!$B$2:$B$400,$A11,Passages!$D$2:$D$400,"Commission analysis",Passages!$P$2:$P$400,1) -> 0 | M11: =COUNTIFS(Passages!$B$2:$B$400,$A11,Passages!$D$2:$D$400,"Commission analysis",Passages!$Q$2:$Q$400,1) -> 0 | N11: =IF(B11=0,"",IF((D11+E11+F11)>0,1,0)) | O11: =IF(B11=0,"",IF(C11>0,1,0)) | P11: =IF((D11+E11+F11)+C11=0,"",(D11+E11+F11)/((D11+E11+F11)+C11))
A12: =Cases!A12 -> P10 | B12: =COUNTIFS(Passages!$B$2:$B$400,$A12,Passages!$D$2:$D$400,"Commission analysis") -> 0 | C12: =COUNTIFS(Passages!$B$2:$B$400,$A12,Passages!$D$2:$D$400,"Commission analysis",Passages!$F$2:$F$400,1) -> 0 | D12: =COUNTIFS(Passages!$B$2:$B$400,$A12,Passages!$D$2:$D$400,"Commission analysis",Passages!$H$2:$H$400,1) -> 0 | E12: =COUNTIFS(Passages!$B$2:$B$400,$A12,Passages!$D$2:$D$400,"Commission analysis",Passages!$I$2:$I$400,1) -> 0 | F12: =COUNTIFS(Passages!$B$2:$B$400,$A12,Passages!$D$2:$D$400,"Commission analysis",Passages!$J$2:$J$400,1) -> 0 | G12: =COUNTIFS(Passages!$B$2:$B$400,$A12,Passages!$D$2:$D$400,"Commission analysis",Passages!$K$2:$K$400,1) -> 0 | H12: =COUNTIFS(Passages!$B$2:$B$400,$A12,Passages!$D$2:$D$400,"Commission analysis",Passages!$L$2:$L$400,1) -> 0 | I12: =COUNTIFS(Passages!$B$2:$B$400,$A12,Passages!$D$2:$D$400,"Commission analysis",Passages!$M$2:$M$400,1) -> 0 | J12: =COUNTIFS(Passages!$B$2:$B$400,$A12,Passages!$D$2:$D$400,"Commission analysis",Passages!$N$2:$N$400,1) -> 0 | K12: =COUNTIFS(Passages!$B$2:$B$400,$A12,Passages!$D$2:$D$400,"Commission analysis",Passages!$O$2:$O$400,1) -> 0 | L12: =COUNTIFS(Passages!$B$2:$B$400,$A12,Passages!$D$2:$D$400,"Commission analysis",Passages!$P$2:$P$400,1) -> 0 | M12: =COUNTIFS(Passages!$B$2:$B$400,$A12,Passages!$D$2:$D$400,"Commission analysis",Passages!$Q$2:$Q$400,1) -> 0 | N12: =IF(B12=0,"",IF((D12+E12+F12)>0,1,0)) | O12: =IF(B12=0,"",IF(C12>0,1,0)) | P12: =IF((D12+E12+F12)+C12=0,"",(D12+E12+F12)/((D12+E12+F12)+C12))
A13: =Cases!A13 -> P11 | B13: =COUNTIFS(Passages!$B$2:$B$400,$A13,Passages!$D$2:$D$400,"Commission analysis") -> 0 | C13: =COUNTIFS(Passages!$B$2:$B$400,$A13,Passages!$D$2:$D$400,"Commission analysis",Passages!$F$2:$F$400,1) -> 0 | D13: =COUNTIFS(Passages!$B$2:$B$400,$A13,Passages!$D$2:$D$400,"Commission analysis",Passages!$H$2:$H$400,1) -> 0 | E13: =COUNTIFS(Passages!$B$2:$B$400,$A13,Passages!$D$2:$D$400,"Commission analysis",Passages!$I$2:$I$400,1) -> 0 | F13: =COUNTIFS(Passages!$B$2:$B$400,$A13,Passages!$D$2:$D$400,"Commission analysis",Passages!$J$2:$J$400,1) -> 0 | G13: =COUNTIFS(Passages!$B$2:$B$400,$A13,Passages!$D$2:$D$400,"Commission analysis",Passages!$K$2:$K$400,1) -> 0 | H13: =COUNTIFS(Passages!$B$2:$B$400,$A13,Passages!$D$2:$D$400,"Commission analysis",Passages!$L$2:$L$400,1) -> 0 | I13: =COUNTIFS(Passages!$B$2:$B$400,$A13,Passages!$D$2:$D$400,"Commission analysis",Passages!$M$2:$M$400,1) -> 0 | J13: =COUNTIFS(Passages!$B$2:$B$400,$A13,Passages!$D$2:$D$400,"Commission analysis",Passages!$N$2:$N$400,1) -> 0 | K13: =COUNTIFS(Passages!$B$2:$B$400,$A13,Passages!$D$2:$D$400,"Commission analysis",Passages!$O$2:$O$400,1) -> 0 | L13: =COUNTIFS(Passages!$B$2:$B$400,$A13,Passages!$D$2:$D$400,"Commission analysis",Passages!$P$2:$P$400,1) -> 0 | M13: =COUNTIFS(Passages!$B$2:$B$400,$A13,Passages!$D$2:$D$400,"Commission analysis",Passages!$Q$2:$Q$400,1) -> 0 | N13: =IF(B13=0,"",IF((D13+E13+F13)>0,1,0)) | O13: =IF(B13=0,"",IF(C13>0,1,0)) | P13: =IF((D13+E13+F13)+C13=0,"",(D13+E13+F13)/((D13+E13+F13)+C13))
... A17: =Cases!A17 -> P15 | B17: =COUNTIFS(Passages!$B$2:$B$400,$A17,Passages!$D$2:$D$400,"Commission analysis") -> 0 | C17: =COUNTIFS(Passages!$B$2:$B$400,$A17,Passages!$D$2:$D$400,"Commission analysis",Passages!$F$2:$F$400,1) -> 0 | D17: =COUNTIFS(Passages!$B$2:$B$400,$A17,Passages!$D$2:$D$400,"Commission analysis",Passages!$H$2:$H$400,1) -> 0 | E17: =COUNTIFS(Passages!$B$2:$B$400,$A17,Passages!$D$2:$D$400,"Commission analysis",Passages!$I$2:$I$400,1) -> 0 | F17: =COUNTIFS(Passages!$B$2:$B$400,$A17,Passages!$D$2:$D$400,"Commission analysis",Passages!$J$2:$J$400,1) -> 0 | G17: =COUNTIFS(Passages!$B$2:$B$400,$A17,Passages!$D$2:$D$400,"Commission analysis",Passages!$K$2:$K$400,1) -> 0 | H17: =COUNTIFS(Passages!$B$2:$B$400,$A17,Passages!$D$2:$D$400,"Commission analysis",Passages!$L$2:$L$400,1) -> 0 | I17: =COUNTIFS(Passages!$B$2:$B$400,$A17,Passages!$D$2:$D$400,"Commission analysis",Passages!$M$2:$M$400,1) -> 0 | J17: =COUNTIFS(Passages!$B$2:$B$400,$A17,Passages!$D$2:$D$400,"Commission analysis",Passages!$N$2:$N$400,1) -> 0 | K17: =COUNTIFS(Passages!$B$2:$B$400,$A17,Passages!$D$2:$D$400,"Commission analysis",Passages!$O$2:$O$400,1) -> 0 | L17: =COUNTIFS(Passages!$B$2:$B$400,$A17,Passages!$D$2:$D$400,"Commission analysis",Passages!$P$2:$P$400,1) -> 0 | M17: =COUNTIFS(Passages!$B$2:$B$400,$A17,Passages!$D$2:$D$400,"Commission analysis",Passages!$Q$2:$Q$400,1) -> 0 | N17: =IF(B17=0,"",IF((D17+E17+F17)>0,1,0)) | O17: =IF(B17=0,"",IF(C17>0,1,0)) | P17: =IF((D17+E17+F17)+C17=0,"",(D17+E17+F17)/((D17+E17+F17)+C17))

Sheet Reliability
A1: passage_id | B1: code | C1: coding_A | D1: coding_B | F1: code | G1: n_pairs | H1: both_1 | I1: both_0 | J1: A_yes | K1: B_yes | L1: observed_agree | M1: expected_agree | N1: kappa | O1: meets_0.70
F2: MKT | G2: =COUNTIFS($B$2:$B$601,F2,$C$2:$C$601,"<>",$D$2:$D$601,"<>") -> 0 | H2: =COUNTIFS($B$2:$B$601,F2,$C$2:$C$601,1,$D$2:$D$601,1) -> 0 | I2: =COUNTIFS($B$2:$B$601,F2,$C$2:$C$601,0,$D$2:$D$601,0) -> 0 | J2: =COUNTIFS($B$2:$B$601,F2,$C$2:$C$601,1,$D$2:$D$601,"<>") -> 0 | K2: =COUNTIFS($B$2:$B$601,F2,$D$2:$D$601,1,$C$2:$C$601,"<>") -> 0 | L2: =IF(G2=0,"",(H2+I2)/G2) | M2: =IF(G2=0,"",(J2/G2)*(K2/G2)+(1-J2/G2)*(1-K2/G2)) | N2: =IF(OR(G2=0,M2=1),"",(L2-M2)/(1-M2)) | O2: =IF(N2="","",IF(N2>=0.7,"Yes","Rewrite"))
F3: PEER | G3: =COUNTIFS($B$2:$B$601,F3,$C$2:$C$601,"<>",$D$2:$D$601,"<>") -> 0 | H3: =COUNTIFS($B$2:$B$601,F3,$C$2:$C$601,1,$D$2:$D$601,1) -> 0 | I3: =COUNTIFS($B$2:$B$601,F3,$C$2:$C$601,0,$D$2:$D$601,0) -> 0 | J3: =COUNTIFS($B$2:$B$601,F3,$C$2:$C$601,1,$D$2:$D$601,"<>") -> 0 | K3: =COUNTIFS($B$2:$B$601,F3,$D$2:$D$601,1,$C$2:$C$601,"<>") -> 0 | L3: =IF(G3=0,"",(H3+I3)/G3) | M3: =IF(G3=0,"",(J3/G3)*(K3/G3)+(1-J3/G3)*(1-K3/G3)) | N3: =IF(OR(G3=0,M3=1),"",(L3-M3)/(1-M3)) | O3: =IF(N3="","",IF(N3>=0.7,"Yes","Rewrite"))
F4: OWN | G4: =COUNTIFS($B$2:$B$601,F4,$C$2:$C$601,"<>",$D$2:$D$601,"<>") -> 0 | H4: =COUNTIFS($B$2:$B$601,F4,$C$2:$C$601,1,$D$2:$D$601,1) -> 0 | I4: =COUNTIFS($B$2:$B$601,F4,$C$2:$C$601,0,$D$2:$D$601,0) -> 0 | J4: =COUNTIFS($B$2:$B$601,F4,$C$2:$C$601,1,$D$2:$D$601,"<>") -> 0 | K4: =COUNTIFS($B$2:$B$601,F4,$D$2:$D$601,1,$C$2:$C$601,"<>") -> 0 | L4: =IF(G4=0,"",(H4+I4)/G4) | M4: =IF(G4=0,"",(J4/G4)*(K4/G4)+(1-J4/G4)*(1-K4/G4)) | N4: =IF(OR(G4=0,M4=1),"",(L4-M4)/(1-M4)) | O4: =IF(N4="","",IF(N4>=0.7,"Yes","Rewrite"))
F5: GRAD | G5: =COUNTIFS($B$2:$B$601,F5,$C$2:$C$601,"<>",$D$2:$D$601,"<>") -> 0 | H5: =COUNTIFS($B$2:$B$601,F5,$C$2:$C$601,1,$D$2:$D$601,1) -> 0 | I5: =COUNTIFS($B$2:$B$601,F5,$C$2:$C$601,0,$D$2:$D$601,0) -> 0 | J5: =COUNTIFS($B$2:$B$601,F5,$C$2:$C$601,1,$D$2:$D$601,"<>") -> 0 | K5: =COUNTIFS($B$2:$B$601,F5,$D$2:$D$601,1,$C$2:$C$601,"<>") -> 0 | L5: =IF(G5=0,"",(H5+I5)/G5) | M5: =IF(G5=0,"",(J5/G5)*(K5/G5)+(1-J5/G5)*(1-K5/G5)) | N5: =IF(OR(G5=0,M5=1),"",(L5-M5)/(1-M5)) | O5: =IF(N5="","",IF(N5>=0.7,"Yes","Rewrite"))
F6: LAW | G6: =COUNTIFS($B$2:$B$601,F6,$C$2:$C$601,"<>",$D$2:$D$601,"<>") -> 0 | H6: =COUNTIFS($B$2:$B$601,F6,$C$2:$C$601,1,$D$2:$D$601,1) -> 0 | I6: =COUNTIFS($B$2:$B$601,F6,$C$2:$C$601,0,$D$2:$D$601,0) -> 0 | J6: =COUNTIFS($B$2:$B$601,F6,$C$2:$C$601,1,$D$2:$D$601,"<>") -> 0 | K6: =COUNTIFS($B$2:$B$601,F6,$D$2:$D$601,1,$C$2:$C$601,"<>") -> 0 | L6: =IF(G6=0,"",(H6+I6)/G6) | M6: =IF(G6=0,"",(J6/G6)*(K6/G6)+(1-J6/G6)*(1-K6/G6)) | N6: =IF(OR(G6=0,M6=1),"",(L6-M6)/(1-M6)) | O6: =IF(N6="","",IF(N6>=0.7,"Yes","Rewrite"))
F7: CAP | G7: =COUNTIFS($B$2:$B$601,F7,$C$2:$C$601,"<>",$D$2:$D$601,"<>") -> 0 | H7: =COUNTIFS($B$2:$B$601,F7,$C$2:$C$601,1,$D$2:$D$601,1) -> 0 | I7: =COUNTIFS($B$2:$B$601,F7,$C$2:$C$601,0,$D$2:$D$601,0) -> 0 | J7: =COUNTIFS($B$2:$B$601,F7,$C$2:$C$601,1,$D$2:$D$601,"<>") -> 0 | K7: =COUNTIFS($B$2:$B$601,F7,$D$2:$D$601,1,$C$2:$C$601,"<>") -> 0 | L7: =IF(G7=0,"",(H7+I7)/G7) | M7: =IF(G7=0,"",(J7/G7)*(K7/G7)+(1-J7/G7)*(1-K7/G7)) | N7: =IF(OR(G7=0,M7=1),"",(L7-M7)/(1-M7)) | O7: =IF(N7="","",IF(N7>=0.7,"Yes","Rewrite"))
F8: RISK | G8: =COUNTIFS($B$2:$B$601,F8,$C$2:$C$601,"<>",$D$2:$D$601,"<>") -> 0 | H8: =COUNTIFS($B$2:$B$601,F8,$C$2:$C$601,1,$D$2:$D$601,1) -> 0 | I8: =COUNTIFS($B$2:$B$601,F8,$C$2:$C$601,0,$D$2:$D$601,0) -> 0 | J8: =COUNTIFS($B$2:$B$601,F8,$C$2:$C$601,1,$D$2:$D$601,"<>") -> 0 | K8: =COUNTIFS($B$2:$B$601,F8,$D$2:$D$601,1,$C$2:$C$601,"<>") -> 0 | L8: =IF(G8=0,"",(H8+I8)/G8) | M8: =IF(G8=0,"",(J8/G8)*(K8/G8)+(1-J8/G8)*(1-K8/G8)) | N8: =IF(OR(G8=0,M8=1),"",(L8-M8)/(1-M8)) | O8: =IF(N8="","",IF(N8>=0.7,"Yes","Rewrite"))
F9: AFF | G9: =COUNTIFS($B$2:$B$601,F9,$C$2:$C$601,"<>",$D$2:$D$601,"<>") -> 0 | H9: =COUNTIFS($B$2:$B$601,F9,$C$2:$C$601,1,$D$2:$D$601,1) -> 0 | I9: =COUNTIFS($B$2:$B$601,F9,$C$2:$C$601,0,$D$2:$D$601,0) -> 0 | J9: =COUNTIFS($B$2:$B$601,F9,$C$2:$C$601,1,$D$2:$D$601,"<>") -> 0 | K9: =COUNTIFS($B$2:$B$601,F9,$D$2:$D$601,1,$C$2:$C$601,"<>") -> 0 | L9: =IF(G9=0,"",(H9+I9)/G9) | M9: =IF(G9=0,"",(J9/G9)*(K9/G9)+(1-J9/G9)*(1-K9/G9)) | N9: =IF(OR(G9=0,M9=1),"",(L9-M9)/(1-M9)) | O9: =IF(N9="","",IF(N9>=0.7,"Yes","Rewrite"))
F10: PERF | G10: =COUNTIFS($B$2:$B$601,F10,$C$2:$C$601,"<>",$D$2:$D$601,"<>") -> 0 | H10: =COUNTIFS($B$2:$B$601,F10,$C$2:$C$601,1,$D$2:$D$601,1) -> 0 | I10: =COUNTIFS($B$2:$B$601,F10,$C$2:$C$601,0,$D$2:$D$601,0) -> 0 | J10: =COUNTIFS($B$2:$B$601,F10,$C$2:$C$601,1,$D$2:$D$601,"<>") -> 0 | K10: =COUNTIFS($B$2:$B$601,F10,$D$2:$D$601,1,$C$2:$C$601,"<>") -> 0 | L10: =IF(G10=0,"",(H10+I10)/G10) | M10: =IF(G10=0,"",(J10/G10)*(K10/G10)+(1-J10/G10)*(1-K10/G10)) | N10: =IF(OR(G10=0,M10=1),"",(L10-M10)/(1-M10)) | O10: =IF(N10="","",IF(N10>=0.7,"Yes","Rewrite"))
F11: DEF | G11: =COUNTIFS($B$2:$B$601,F11,$C$2:$C$601,"<>",$D$2:$D$601,"<>") -> 0 | H11: =COUNTIFS($B$2:$B$601,F11,$C$2:$C$601,1,$D$2:$D$601,1) -> 0 | I11: =COUNTIFS($B$2:$B$601,F11,$C$2:$C$601,0,$D$2:$D$601,0) -> 0 | J11: =COUNTIFS($B$2:$B$601,F11,$C$2:$C$601,1,$D$2:$D$601,"<>") -> 0 | K11: =COUNTIFS($B$2:$B$601,F11,$D$2:$D$601,1,$C$2:$C$601,"<>") -> 0 | L11: =IF(G11=0,"",(H11+I11)/G11) | M11: =IF(G11=0,"",(J11/G11)*(K11/G11)+(1-J11/G11)*(1-K11/G11)) | N11: =IF(OR(G11=0,M11=1),"",(L11-M11)/(1-M11)) | O11: =IF(N11="","",IF(N11>=0.7,"Yes","Rewrite"))
F12: CONC | G12: =COUNTIFS($B$2:$B$601,F12,$C$2:$C$601,"<>",$D$2:$D$601,"<>") -> 0 | H12: =COUNTIFS($B$2:$B$601,F12,$C$2:$C$601,1,$D$2:$D$601,1) -> 0 | I12: =COUNTIFS($B$2:$B$601,F12,$C$2:$C$601,0,$D$2:$D$601,0) -> 0 | J12: =COUNTIFS($B$2:$B$601,F12,$C$2:$C$601,1,$D$2:$D$601,"<>") -> 0 | K12: =COUNTIFS($B$2:$B$601,F12,$D$2:$D$601,1,$C$2:$C$601,"<>") -> 0 | L12: =IF(G12=0,"",(H12+I12)/G12) | M12: =IF(G12=0,"",(J12/G12)*(K12/G12)+(1-J12/G12)*(1-K12/G12)) | N12: =IF(OR(G12=0,M12=1),"",(L12-M12)/(1-M12)) | O12: =IF(N12="","",IF(N12>=0.7,"Yes","Rewrite"))
F14: One row per passage × code. coding_A = first pass, coding_B = re-code or second coder (0/1). Kappa is blank when a code never varies.

Sheet Summary
A1: Pilot summary — pilot rows P01–P15 only (example row excluded)
A3: FEASIBILITY
A4: Orders coded (award entered) | B4: =COUNT(Cases!$X$3:$X$17) -> 0 | C4: Target: 15
A5: Fully litigated orders | B5: =COUNTIFS(Cases!$I$3:$I$17,"Fully litigated") -> 0
A6: Median minutes per order | B6: =IFERROR(MEDIAN(Cases!$AN$3:$AN$17),"") | C6: Scales the full-study time budget
A7: Share of orders with advocate recommendation recovered | B7: =IFERROR(COUNT(Cases!$S$3:$S$17)/COUNT(Cases!$X$3:$X$17),"")
A8: DESCRIPTIVE (not a test of the hypothesis)
A9: Share of orders flagged conclusory | B9: =IFERROR(COUNTIF(Cases!$AJ$3:$AJ$17,"Y")/(COUNTIF(Cases!$AJ$3:$AJ$17,"Y")+COUNTIF(Cases!$AJ$3:$AJ$17,"N")),"") | C9: Rule 6
A10: Mean split position (0 = advocate, 1 = utility) | B10: =IFERROR(AVERAGE(Cases!$AQ$3:$AQ$17),"")
A11: Share of awards closer to national benchmark than record midpoint | B11: =IFERROR(COUNTIF(Cases!$AT$3:$AT$17,"National avg")/(COUNTIF(Cases!$AT$3:$AT$17,"National avg")+COUNTIF(Cases!$AT$3:$AT$17,"Record midpoint")+COUNTIF(Cases!$AT$3:$AT$17,"Tie")),"") | C11: Descriptive preview of H1
A12: Mean change vs. prior authorized ROE | B12: =IFERROR(AVERAGE(Cases!$AU$3:$AU$17),"")
A13: Share of orders with any anchor reasoning (PEER/OWN/GRAD) | B13: =IFERROR(SUM(Case_Codes!$N$3:$N$17)/COUNT(Case_Codes!$N$3:$N$17),"") | C13: Commission analysis only
A14: Share of orders with any market reasoning (MKT) | B14: =IFERROR(SUM(Case_Codes!$O$3:$O$17)/COUNT(Case_Codes!$O$3:$O$17),"") | C14: Commission analysis only
A15: Mean anchor share | B15: =IFERROR(AVERAGE(Case_Codes!$P$3:$P$17),"") | C15: 0 = all market, 1 = all reference-point
A16: BY INTEREST-RATE REGIME (sampling rule needs 5+ Pre and 5+ Post)
A17: Orders: Pre (2019-21) | B17: =COUNTIF(Cases!$BE$3:$BE$17,"Pre (2019-21)") -> 0
A18: Orders: Transition (2022) | B18: =COUNTIF(Cases!$BE$3:$BE$17,"Transition (2022)") -> 0 | C18: Allowed, but counts toward neither quota
A19: Orders: Post (2023-) | B19: =COUNTIF(Cases!$BE$3:$BE$17,"Post (2023-)") -> 0
A20: Mean change in 10-yr Treasury since prior order: Post | B20: =IFERROR(AVERAGEIFS(Cases!$BC$3:$BC$17,Cases!$BE$3:$BE$17,"Post (2023-)"),"") | C20: How big the shock was for these utilities
A21: Mean change in ROE vs prior award: Pre | B21: =IFERROR(AVERAGEIFS(Cases!$AU$3:$AU$17,Cases!$BE$3:$BE$17,"Pre (2019-21)"),"")
A22: Mean change in ROE vs prior award: Post | B22: =IFERROR(AVERAGEIFS(Cases!$AU$3:$AU$17,Cases!$BE$3:$BE$17,"Post (2023-)"),"") | C22: Compare with the Treasury change above
A23: Mean split position: Pre | B23: =IFERROR(AVERAGEIFS(Cases!$AQ$3:$AQ$17,Cases!$BE$3:$BE$17,"Pre (2019-21)"),"") | C23: 0 = advocate, 1 = utility
A24: Mean split position: Post | B24: =IFERROR(AVERAGEIFS(Cases!$AQ$3:$AQ$17,Cases!$BE$3:$BE$17,"Post (2023-)"),"")
A25: Mean request revision (final minus initial ask) | B25: =IFERROR(AVERAGE(Cases!$BD$3:$BD$17),"") | C25: Negative = utilities lowered asks mid-case
A26: SHARE OF COMMISSION-ANALYSIS PASSAGES WITH EACH CODE
A27: MKT | B27: =IFERROR(SUM(Case_Codes!$C$3:$C$17)/SUM(Case_Codes!$B$3:$B$17),"")
A28: PEER | B28: =IFERROR(SUM(Case_Codes!$D$3:$D$17)/SUM(Case_Codes!$B$3:$B$17),"")
A29: OWN | B29: =IFERROR(SUM(Case_Codes!$E$3:$E$17)/SUM(Case_Codes!$B$3:$B$17),"")
A30: GRAD | B30: =IFERROR(SUM(Case_Codes!$F$3:$F$17)/SUM(Case_Codes!$B$3:$B$17),"")
A31: LAW | B31: =IFERROR(SUM(Case_Codes!$G$3:$G$17)/SUM(Case_Codes!$B$3:$B$17),"")
A32: CAP | B32: =IFERROR(SUM(Case_Codes!$H$3:$H$17)/SUM(Case_Codes!$B$3:$B$17),"")
A33: RISK | B33: =IFERROR(SUM(Case_Codes!$I$3:$I$17)/SUM(Case_Codes!$B$3:$B$17),"")
A34: AFF | B34: =IFERROR(SUM(Case_Codes!$J$3:$J$17)/SUM(Case_Codes!$B$3:$B$17),"")
A35: PERF | B35: =IFERROR(SUM(Case_Codes!$K$3:$K$17)/SUM(Case_Codes!$B$3:$B$17),"")
A36: DEF | B36: =IFERROR(SUM(Case_Codes!$L$3:$L$17)/SUM(Case_Codes!$B$3:$B$17),"")
A37: CONC | B37: =IFERROR(SUM(Case_Codes!$M$3:$M$17)/SUM(Case_Codes!$B$3:$B$17),"")

Sheet Lists
A1: State | B1: Service | C1: Segment | D1: Decision | E1: YN | F1: Selection | G1: Section | H1: Stance | I1: Method | J1: Code | K1: Binary | L1: SampleStatus
A2: CT | B2: Electric | C2: Distribution | D2: Fully litigated | E2: Y | F2: Appointed | G2: Positions of parties | H2: Relied on | I2: DCF | J2: MKT | K2: 0 | L2: Sample
A3: MA | B3: Gas | C3: Vertically integrated | D3: Partial settlement | E3: N | F3: Elected | G3: ALJ recommendation | H3: Considered | I3: CAPM/ECAPM | J3: PEER | K3: 1 | L3: Included by design
A4: ME | B4: Combined | C4: Transmission | D4: Full settlement | G4: Commission analysis | H4: Rejected | I4: Risk premium | J4: OWN | L4: Substitute (settled)
A5: NH | C5: Gas LDC | G5: Other | H5: Summarized only | I5: Expected earnings | J5: GRAD
A6: RI | I6: Multiple | J6: LAW
A7: VT | I7: Unspecified | J7: CAP
I8: n.a. | J8: RISK
J9: AFF
J10: PERF
J11: DEF
J12: CONC
